interval_py-1.0.5.dist-info/licenses/LICENSE
intervalpy/__init__.py
intervalpy/interval.py
interval_py-1.0.5.dist-info/METADATA
interval_py-1.0.5.dist-info/WHEEL
interval_py-1.0.5.dist-info/top_level.txt
interval_py-1.0.5.dist-info/RECORD
