Metadata-Version: 2.4
Name: interval-py
Version: 1.0.5
Summary: Interval arithmetic library for Python
Home-page: https://github.com/artemmam/intervalpy
Author: Artem Maminov, Mikhail Posypkin
Author-email: amaminov@hse.ru
Project-URL: Bug Tracker, https://github.com/amaminov/intervalpy/issues
Classifier: Programming Language :: Python :: 3
Classifier: License :: OSI Approved :: MIT License
Classifier: Operating System :: OS Independent
Requires-Python: >=3.6
License-File: LICENSE
Dynamic: license-file
